Metadata-Version: 2.1
Name: sharefile-webui
Version: 1.7.7
Summary: WEB APP for sharing files via URL links.
Home-page: https://gitlab.com/alda78/sharefile-webui
Author: Ales Adamek
Author-email: alda78@seznam.cz
License: MIT
Platform: UNKNOWN
Classifier: Programming Language :: Python :: 3
Classifier: License :: OSI Approved :: MIT License
Classifier: Operating System :: OS Independent
Requires-Python: >=3.8
Requires-Dist: flask
Requires-Dist: flask-httpauth
Requires-Dist: flask-restful
Requires-Dist: markdown
Requires-Dist: requests
Requires-Dist: werkzeug
